verilog/mux2x1.v
module mux2x1_str(output out, input a,b,sel);
wire selb,out1,out2;
and A1(out1,a,sel);
and A2(out2,b,selb);
not INV1(selb,sel);
or O1(out,out1,out2);
endmodule

verilog/tb_mux2x1.v
`include"mux2x1.v"
module mux2x1_str_tb();
reg a,b,sel;
wire out;
mux2x1_str DUT(out,a,b,sel);
initial
begin
$monitor("At time %t,a=(%0d),b=(%0d),sel=(%0d)",$time,a,b,sel);
$dumpfile("mux2x1_str_tb.vcd");
$dumpvars(0, mux2x1_str_tb);
a = 0; b = 0; sel = 0; #10;
a = 0; b = 0; sel = 1; #10;
a = 0; b = 1; sel = 0; #10;
a = 0; b = 1; sel = 1; #10;
a = 1; b = 0; sel = 0; #10;
a = 1; b = 0; sel = 1; #10;
a = 1; b = 1; sel = 0; #10;
a = 1; b = 1; sel = 1; #10;
end
endmodule

verilog/mux2x1_str_tb.vcd
$date
	Tue Jan 11 10:02:52 2022
$end
$version
	Icarus Verilog
$end
$timescale
	1s
$end
$scope module mux2x1_str_tb $end
$var wire 1 ! out $end
$var reg 1 " a $end
$var reg 1 # b $end
$var reg 1 $ sel $end
$scope module DUT $end
$var wire 1 " a $end
$var wire 1 # b $end
$var wire 1 ! out $end
$var wire 1 % out1 $end
$var wire 1 & out2 $end
$var wire 1 $ sel $end
$var wire 1 ' selb $end
$upscope $end
$upscope $end
$enddefinitions $end
#0
$dumpvars
1'
0&
0%
0$
0#
0"
0!
$end
#10
0'
1$
#20
1!
1&
1'
0$
1#
#30
0!
0&
0'
1$
#40
1'
0$
0#
1"
#50
1!
1%
0'
1$
#60
1&
0%
1'
0$
1#
#70
0&
1%
0'
1$
